bmitools/__init__.py
bmitools/bmitools.py
bmitools/calcium.py
bmitools/analysis/__init__.py
bmitools/utils/__init__.py
bmitools/utils/utils.py
bmitools/utils/.ipynb_checkpoints/utils-checkpoint.py
bmitools/utils/__pycache__/__init__.cpython-38.pyc
bmitools/utils/__pycache__/utils.cpython-38.pyc
bmitools/utils/animal_database/__init__.py
bmitools/utils/animal_database/animal_database.py
bmitools/utils/animal_database/.ipynb_checkpoints/animal_database-checkpoint.ipynb
bmitools/utils/animal_database/__pycache__/__init__.cpython-38.pyc
bmitools/utils/animal_database/__pycache__/animal_database.cpython-38.pyc
bmitools/utils/calcium/__init__.py
bmitools/utils/calcium/calcium.py
bmitools/utils/calcium/.ipynb_checkpoints/calcium-checkpoint.py
bmitools/utils/calcium/__pycache__/__init__.cpython-38.pyc
bmitools/utils/calcium/__pycache__/calcium.cpython-38.pyc
bmitools/utils/network/__init__.py
bmitools/utils/network/network.py
bmitools/utils/network/.ipynb_checkpoints/calcium-checkpoint.py
bmitools/utils/network/.ipynb_checkpoints/wheel-checkpoint.py
bmitools/utils/network/__pycache__/__init__.cpython-38.pyc
bmitools/utils/network/__pycache__/network.cpython-38.pyc
bmitools/utils/network/__pycache__/pca.cpython-38.pyc
bmitools/utils/network/__pycache__/wheel.cpython-38.pyc
bmitools/utils/wheel/__init__.py
bmitools/utils/wheel/wheel.py
bmitools/utils/wheel/.ipynb_checkpoints/calcium-checkpoint.py
bmitools/utils/wheel/.ipynb_checkpoints/wheel-checkpoint.py
bmitools/utils/wheel/__pycache__/__init__.cpython-38.pyc
bmitools/utils/wheel/__pycache__/pca.cpython-38.pyc
bmitools/utils/wheel/__pycache__/wheel.cpython-38.pyc
bmitools-0.1.9.dist-info/LICENSE
bmitools-0.1.9.dist-info/METADATA
bmitools-0.1.9.dist-info/WHEEL
bmitools-0.1.9.dist-info/top_level.txt
bmitools-0.1.9.dist-info/RECORD
