Metadata-Version: 2.1
Name: bmitools
Version: 0.1.9
License-File: LICENSE
Requires-Dist: numpy
Requires-Dist: tqdm
Requires-Dist: scipy
Requires-Dist: matplotlib
Requires-Dist: pyyaml
Requires-Dist: networkx
Requires-Dist: scikit-learn
Requires-Dist: pandas
Requires-Dist: opencv-python
Requires-Dist: parmap
